subtitle/__init__.py
subtitle/subtrans.py
subtranslate-0.2.dist-info/METADATA
subtranslate-0.2.dist-info/WHEEL
subtranslate-0.2.dist-info/top_level.txt
subtranslate-0.2.dist-info/RECORD
