Metadata-Version: 2.1
Name: subtranslate
Version: 0.2
Author: kumaresankp
Requires-Dist: pysrt
Requires-Dist: translate
